fhrs/__init__.py
fhrs/fhrs.py
pythonfhrs-0.2.0.dist-info/AUTHORS.rst
pythonfhrs-0.2.0.dist-info/LICENSE
pythonfhrs-0.2.0.dist-info/METADATA
pythonfhrs-0.2.0.dist-info/WHEEL
pythonfhrs-0.2.0.dist-info/top_level.txt
pythonfhrs-0.2.0.dist-info/RECORD
